metpyqc/__init__.py
metpyqc/calculate.py
metpyqc/internal.py
metpyqc/range.py
metpyqc/reconstruct.py
metpyqc/spatial.py
metpyqc/temporal.py
MetPyQC-0.1.1.dist-info/LICENSE
MetPyQC-0.1.1.dist-info/METADATA
MetPyQC-0.1.1.dist-info/WHEEL
MetPyQC-0.1.1.dist-info/top_level.txt
MetPyQC-0.1.1.dist-info/RECORD
