Metadata-Version: 2.1
Name: MetPyQC
Version: 0.1.1
Summary: Quality control and reconstruction of meteorological data
Home-page: https://github.com/silve92/MetPyQC
Author: Lorenzo Silvestri
Author-email: lorenzo.silvestri.eng@gmail.com
License: MIT license
Platform: UNKNOWN
Classifier: Programming Language :: Python :: 3
Classifier: License :: OSI Approved :: MIT License
Classifier: Operating System :: OS Independent
Classifier: Topic :: Scientific/Engineering :: Atmospheric Science
Requires-Python: >=3.6
License-File: LICENSE
Requires-Dist: numpy (>=1.20.1)
Requires-Dist: scipy (>=1.6.0)
Requires-Dist: pandas (>=1.1.3)
Requires-Dist: scikit-learn (>=0.23.2)
Requires-Dist: tqdm (>=4.42.1)
